py_crave_sync/__init__.py
py_crave_sync/server.py
py_crave_sync-0.1.2.dist-info/METADATA
py_crave_sync-0.1.2.dist-info/WHEEL
py_crave_sync-0.1.2.dist-info/entry_points.txt
py_crave_sync-0.1.2.dist-info/top_level.txt
py_crave_sync-0.1.2.dist-info/RECORD
